{
  "@context": {
    "@vocab": "http://www.w3.org/ns/earl#",
    "earl": "http://www.w3.org/ns/earl#",
    "WCAG": "https://www.w3.org/TR/WCAG/#",
    "WCAG10": "https://www.w3.org/TR/WCAG10/#",
    "WCAG2": "https://www.w3.org/TR/WCAG2/#",
    "WCAG20": "https://www.w3.org/TR/WCAG20/#",
    "WCAG21": "https://www.w3.org/TR/WCAG21/#",
    "WCAG22": "https://www.w3.org/TR/WCAG22/#",
    "WCAG30": "https://www.w3.org/TR/wcag-3.0/#",
    "dct": "http://purl.org/dc/terms/",
    "sch": "https://schema.org/",
    "doap": "http://usefulinc.com/ns/doap#",
    "foaf": "http://xmlns.com/foaf/0.1/",
    "ptr": "http://www.w3.org/2009/pointers#",
    "cnt": "http://www.w3.org/2011/content#",
    "http-vocab": "http://www.w3.org/2011/http#",
    "WebPage": "sch:WebPage",
    "url": "dct:source",
    "source": "dct:source",
    "redirectedTo": "dct:source",
    "title": "dct:title",
    "Project": "doap:Project",
    "Version": "doap:Version",
    "name": "doap:name",
    "description": "doap:description",
    "shortdesc": "doap:shortdesc",
    "created": "doap:created",
    "release": "doap:release",
    "revision": "doap:revision",
    "homepage": {
      "@id": "doap:homepage",
      "@type": "@id"
    },
    "license": {
      "@id": "doap:license",
      "@type": "@id"
    },
    "assertedThat": {
      "@reverse": "assertedBy"
    },
    "assertions": {
      "@reverse": "subject"
    },
    "assertedBy": {
      "@type": "@id"
    },
    "outcome": {
      "@type": "@id"
    },
    "mode": {
      "@type": "@id"
    },
    "pointer": {
      "@type": "ptr:CSSSelectorPointer"
    },
    "isPartOf": {
      "@id": "dct:isPartOf",
      "@type": "@id"
    }
  },
  "@graph": [
    {
      "@id": "https://www.w3.org/WAI/content-assets/wcag-act-rules/testcases/ucwvc8/dbc6a8459d78e618aab31e7051b4ce69b59c7f2f.html",
      "@type": "TestSubject",
      "dct:hasPart": [
        {
          "@type": [
            "http-vocab:Message",
            "http-vocab:Request"
          ],
          "http-vocab:body": {
            "@type": [
              "cnt:Content",
              "cnt:ContentAsText"
            ],
            "cnt:characterEncoding": "utf-8",
            "cnt:chars": ""
          },
          "http-vocab:headers": {
            "@list": []
          },
          "http-vocab:methodName": "GET",
          "http-vocab:requestURI": "https://www.w3.org/WAI/content-assets/wcag-act-rules/testcases/ucwvc8/dbc6a8459d78e618aab31e7051b4ce69b59c7f2f.html"
        },
        {
          "@type": [
            "http-vocab:Message",
            "http-vocab:Response"
          ],
          "http-vocab:body": {
            "@type": [
              "cnt:Content",
              "cnt:ContentAsText"
            ],
            "cnt:characterEncoding": "utf-8",
            "cnt:chars": "<!DOCTYPE html>\n<html>\n\t<p lang=\"en\">\n\t\tThe Accessibility Conformance Testing (ACT) Rules Format 1.0 defines a format for writing accessibility test rules.\n\t\tThese test rules can be used for developing automated testing tools and manual testing methodologies. It provides a\n\t\tcommon format that allows any party involved in accessibility testing to document and share their testing procedures\n\t\tin a robust and understandable manner. This enables transparency and harmonization of testing methods, including\n\t\tmethods implemented by accessibility test tools.\n\t</p>\n</html>"
          },
          "http-vocab:headers": {
            "@list": [
              {
                "@type": "http-vocab:MessageHeader",
                "http-vocab:fieldName": "content-type",
                "http-vocab:fieldValue": "text/html; charset=utf-8"
              }
            ]
          },
          "http-vocab:statusCodeValue": 200
        }
      ],
      "url": "https://www.w3.org/WAI/content-assets/wcag-act-rules/testcases/ucwvc8/dbc6a8459d78e618aab31e7051b4ce69b59c7f2f.html"
    },
    {
      "@type": "Assertion",
      "earl:mode": "earl:automatic",
      "result": {
        "@type": "TestResult",
        "outcome": "earl:inapplicable"
      },
      "subject": {
        "@id": "https://www.w3.org/WAI/content-assets/wcag-act-rules/testcases/ucwvc8/dbc6a8459d78e618aab31e7051b4ce69b59c7f2f.html"
      },
      "test": {
        "@id": "https://alfa.siteimprove.com/rules/sia-r109",
        "@type": [
          "TestCriterion",
          "TestCase"
        ],
        "isPartOf": [
          {
            "@id": "WCAG2:language-of-page",
            "@type": [
              "TestCriterion",
              "TestRequirement"
            ],
            "dct:isPartOf": "https://www.w3.org/TR/WCAG/",
            "title": "Language of Page"
          },
          {
            "@id": "https://www.w3.org/WAI/WCAG21/Techniques/html/H57",
            "@type": [
              "TestCriterion",
              "TestRequirement"
            ],
            "dct:isPartOf": "https://www.w3.org/WAI/WCAG21/Techniques/",
            "title": "Using the language attribute on the HTML element"
          }
        ]
      }
    },
    {
      "@id": "https://www.w3.org/WAI/content-assets/wcag-act-rules/testcases/ucwvc8/80e6225b051ac34c23c7c0ede7d28d426d1be084.html",
      "@type": "TestSubject",
      "dct:hasPart": [
        {
          "@type": [
            "http-vocab:Message",
            "http-vocab:Request"
          ],
          "http-vocab:body": {
            "@type": [
              "cnt:Content",
              "cnt:ContentAsText"
            ],
            "cnt:characterEncoding": "utf-8",
            "cnt:chars": ""
          },
          "http-vocab:headers": {
            "@list": []
          },
          "http-vocab:methodName": "GET",
          "http-vocab:requestURI": "https://www.w3.org/WAI/content-assets/wcag-act-rules/testcases/ucwvc8/80e6225b051ac34c23c7c0ede7d28d426d1be084.html"
        },
        {
          "@type": [
            "http-vocab:Message",
            "http-vocab:Response"
          ],
          "http-vocab:body": {
            "@type": [
              "cnt:Content",
              "cnt:ContentAsText"
            ],
            "cnt:characterEncoding": "utf-8",
            "cnt:chars": "<!DOCTYPE html>\n<html lang=\"fr\">\n\t<head>\n\t\t<title>Paul put dire comment on tape</title>\n\t</head>\n\t<body>\n\t\t<p>Paul put dire comment on tape</p>\n\t</body>\n</html>"
          },
          "http-vocab:headers": {
            "@list": [
              {
                "@type": "http-vocab:MessageHeader",
                "http-vocab:fieldName": "content-type",
                "http-vocab:fieldValue": "text/html; charset=utf-8"
              }
            ]
          },
          "http-vocab:statusCodeValue": 200
        }
      ],
      "url": "https://www.w3.org/WAI/content-assets/wcag-act-rules/testcases/ucwvc8/80e6225b051ac34c23c7c0ede7d28d426d1be084.html"
    },
    {
      "@type": "Assertion",
      "earl:mode": "earl:semiAuto",
      "result": {
        "@type": "TestResult",
        "info": "The document has no identifiable natural language",
        "outcome": "earl:failed",
        "earl:pointer": {
          "@type": [
            "ptr:Pointer",
            "ptr:SinglePointer",
            "ptr:ExpressionPointer",
            "ptr:XPathPointer"
          ],
          "ptr:expression": "/"
        }
      },
      "subject": {
        "@id": "https://www.w3.org/WAI/content-assets/wcag-act-rules/testcases/ucwvc8/80e6225b051ac34c23c7c0ede7d28d426d1be084.html"
      },
      "test": {
        "@id": "https://alfa.siteimprove.com/rules/sia-r109",
        "@type": [
          "TestCriterion",
          "TestCase"
        ],
        "isPartOf": [
          {
            "@id": "WCAG2:language-of-page",
            "@type": [
              "TestCriterion",
              "TestRequirement"
            ],
            "dct:isPartOf": "https://www.w3.org/TR/WCAG/",
            "title": "Language of Page"
          },
          {
            "@id": "https://www.w3.org/WAI/WCAG21/Techniques/html/H57",
            "@type": [
              "TestCriterion",
              "TestRequirement"
            ],
            "dct:isPartOf": "https://www.w3.org/WAI/WCAG21/Techniques/",
            "title": "Using the language attribute on the HTML element"
          }
        ]
      }
    },
    {
      "@id": "https://www.w3.org/WAI/content-assets/wcag-act-rules/testcases/ucwvc8/6616b9ffd712e7789c50b01da8420fd665786677.html",
      "@type": "TestSubject",
      "dct:hasPart": [
        {
          "@type": [
            "http-vocab:Message",
            "http-vocab:Request"
          ],
          "http-vocab:body": {
            "@type": [
              "cnt:Content",
              "cnt:ContentAsText"
            ],
            "cnt:characterEncoding": "utf-8",
            "cnt:chars": ""
          },
          "http-vocab:headers": {
            "@list": []
          },
          "http-vocab:methodName": "GET",
          "http-vocab:requestURI": "https://www.w3.org/WAI/content-assets/wcag-act-rules/testcases/ucwvc8/6616b9ffd712e7789c50b01da8420fd665786677.html"
        },
        {
          "@type": [
            "http-vocab:Message",
            "http-vocab:Response"
          ],
          "http-vocab:body": {
            "@type": [
              "cnt:Content",
              "cnt:ContentAsText"
            ],
            "cnt:characterEncoding": "utf-8",
            "cnt:chars": "<!DOCTYPE html>\n<html lang=\"nl\">\n\t<head>\n\t\t<title>Gelukkig</title>\n\t</head>\n\t<body>\n\t\t<p>The Dutch word \"gelukkig\" has no equivalent in English.</p>\n\t</body>\n</html>"
          },
          "http-vocab:headers": {
            "@list": [
              {
                "@type": "http-vocab:MessageHeader",
                "http-vocab:fieldName": "content-type",
                "http-vocab:fieldValue": "text/html; charset=utf-8"
              }
            ]
          },
          "http-vocab:statusCodeValue": 200
        }
      ],
      "url": "https://www.w3.org/WAI/content-assets/wcag-act-rules/testcases/ucwvc8/6616b9ffd712e7789c50b01da8420fd665786677.html"
    },
    {
      "@type": "Assertion",
      "earl:mode": "earl:semiAuto",
      "result": {
        "@type": "TestResult",
        "info": "The document's `lang` attribute (nl) does not match its language (en)",
        "outcome": "earl:failed",
        "earl:pointer": {
          "@type": [
            "ptr:Pointer",
            "ptr:SinglePointer",
            "ptr:ExpressionPointer",
            "ptr:XPathPointer"
          ],
          "ptr:expression": "/"
        }
      },
      "subject": {
        "@id": "https://www.w3.org/WAI/content-assets/wcag-act-rules/testcases/ucwvc8/6616b9ffd712e7789c50b01da8420fd665786677.html"
      },
      "test": {
        "@id": "https://alfa.siteimprove.com/rules/sia-r109",
        "@type": [
          "TestCriterion",
          "TestCase"
        ],
        "isPartOf": [
          {
            "@id": "WCAG2:language-of-page",
            "@type": [
              "TestCriterion",
              "TestRequirement"
            ],
            "dct:isPartOf": "https://www.w3.org/TR/WCAG/",
            "title": "Language of Page"
          },
          {
            "@id": "https://www.w3.org/WAI/WCAG21/Techniques/html/H57",
            "@type": [
              "TestCriterion",
              "TestRequirement"
            ],
            "dct:isPartOf": "https://www.w3.org/WAI/WCAG21/Techniques/",
            "title": "Using the language attribute on the HTML element"
          }
        ]
      }
    },
    {
      "@id": "https://www.w3.org/WAI/content-assets/wcag-act-rules/testcases/ucwvc8/0f73e7179e17f050380f0ea350d2551611820fd5.html",
      "@type": "TestSubject",
      "dct:hasPart": [
        {
          "@type": [
            "http-vocab:Message",
            "http-vocab:Request"
          ],
          "http-vocab:body": {
            "@type": [
              "cnt:Content",
              "cnt:ContentAsText"
            ],
            "cnt:characterEncoding": "utf-8",
            "cnt:chars": ""
          },
          "http-vocab:headers": {
            "@list": []
          },
          "http-vocab:methodName": "GET",
          "http-vocab:requestURI": "https://www.w3.org/WAI/content-assets/wcag-act-rules/testcases/ucwvc8/0f73e7179e17f050380f0ea350d2551611820fd5.html"
        },
        {
          "@type": [
            "http-vocab:Message",
            "http-vocab:Response"
          ],
          "http-vocab:body": {
            "@type": [
              "cnt:Content",
              "cnt:ContentAsText"
            ],
            "cnt:characterEncoding": "utf-8",
            "cnt:chars": "<!DOCTYPE html>\n<html lang=\"eng\">\n\t<body>\n\t\t<p lang=\"en\">I love ACT rules!</p>\n\t</body>\n</html>"
          },
          "http-vocab:headers": {
            "@list": [
              {
                "@type": "http-vocab:MessageHeader",
                "http-vocab:fieldName": "content-type",
                "http-vocab:fieldValue": "text/html; charset=utf-8"
              }
            ]
          },
          "http-vocab:statusCodeValue": 200
        }
      ],
      "url": "https://www.w3.org/WAI/content-assets/wcag-act-rules/testcases/ucwvc8/0f73e7179e17f050380f0ea350d2551611820fd5.html"
    },
    {
      "@type": "Assertion",
      "earl:mode": "earl:automatic",
      "result": {
        "@type": "TestResult",
        "outcome": "earl:inapplicable"
      },
      "subject": {
        "@id": "https://www.w3.org/WAI/content-assets/wcag-act-rules/testcases/ucwvc8/0f73e7179e17f050380f0ea350d2551611820fd5.html"
      },
      "test": {
        "@id": "https://alfa.siteimprove.com/rules/sia-r109",
        "@type": [
          "TestCriterion",
          "TestCase"
        ],
        "isPartOf": [
          {
            "@id": "WCAG2:language-of-page",
            "@type": [
              "TestCriterion",
              "TestRequirement"
            ],
            "dct:isPartOf": "https://www.w3.org/TR/WCAG/",
            "title": "Language of Page"
          },
          {
            "@id": "https://www.w3.org/WAI/WCAG21/Techniques/html/H57",
            "@type": [
              "TestCriterion",
              "TestRequirement"
            ],
            "dct:isPartOf": "https://www.w3.org/WAI/WCAG21/Techniques/",
            "title": "Using the language attribute on the HTML element"
          }
        ]
      }
    },
    {
      "@id": "https://www.w3.org/WAI/content-assets/wcag-act-rules/testcases/ucwvc8/1b73557d29073ecd327790ca1a6e343b4395b2ab.svg",
      "@type": "TestSubject",
      "dct:hasPart": [
        {
          "@type": [
            "http-vocab:Message",
            "http-vocab:Request"
          ],
          "http-vocab:body": {
            "@type": [
              "cnt:Content",
              "cnt:ContentAsText"
            ],
            "cnt:characterEncoding": "utf-8",
            "cnt:chars": ""
          },
          "http-vocab:headers": {
            "@list": []
          },
          "http-vocab:methodName": "GET",
          "http-vocab:requestURI": "https://www.w3.org/WAI/content-assets/wcag-act-rules/testcases/ucwvc8/1b73557d29073ecd327790ca1a6e343b4395b2ab.svg"
        },
        {
          "@type": [
            "http-vocab:Message",
            "http-vocab:Response"
          ],
          "http-vocab:body": {
            "@type": [
              "cnt:Content",
              "cnt:ContentAsText"
            ],
            "cnt:characterEncoding": "utf-8",
            "cnt:chars": "<svg xmlns=\"http://www.w3.org/2000/svg\" lang=\"fr\"></svg>"
          },
          "http-vocab:headers": {
            "@list": [
              {
                "@type": "http-vocab:MessageHeader",
                "http-vocab:fieldName": "content-type",
                "http-vocab:fieldValue": "image/svg+xml"
              }
            ]
          },
          "http-vocab:statusCodeValue": 200
        }
      ],
      "url": "https://www.w3.org/WAI/content-assets/wcag-act-rules/testcases/ucwvc8/1b73557d29073ecd327790ca1a6e343b4395b2ab.svg"
    },
    {
      "@type": "Assertion",
      "earl:mode": "earl:automatic",
      "result": {
        "@type": "TestResult",
        "outcome": "earl:inapplicable"
      },
      "subject": {
        "@id": "https://www.w3.org/WAI/content-assets/wcag-act-rules/testcases/ucwvc8/1b73557d29073ecd327790ca1a6e343b4395b2ab.svg"
      },
      "test": {
        "@id": "https://alfa.siteimprove.com/rules/sia-r109",
        "@type": [
          "TestCriterion",
          "TestCase"
        ],
        "isPartOf": [
          {
            "@id": "WCAG2:language-of-page",
            "@type": [
              "TestCriterion",
              "TestRequirement"
            ],
            "dct:isPartOf": "https://www.w3.org/TR/WCAG/",
            "title": "Language of Page"
          },
          {
            "@id": "https://www.w3.org/WAI/WCAG21/Techniques/html/H57",
            "@type": [
              "TestCriterion",
              "TestRequirement"
            ],
            "dct:isPartOf": "https://www.w3.org/WAI/WCAG21/Techniques/",
            "title": "Using the language attribute on the HTML element"
          }
        ]
      }
    },
    {
      "@id": "https://www.w3.org/WAI/content-assets/wcag-act-rules/testcases/ucwvc8/b1a2ce0c3435765e96d31a3262f1ed8c1d92f817.html",
      "@type": "TestSubject",
      "dct:hasPart": [
        {
          "@type": [
            "http-vocab:Message",
            "http-vocab:Request"
          ],
          "http-vocab:body": {
            "@type": [
              "cnt:Content",
              "cnt:ContentAsText"
            ],
            "cnt:characterEncoding": "utf-8",
            "cnt:chars": ""
          },
          "http-vocab:headers": {
            "@list": []
          },
          "http-vocab:methodName": "GET",
          "http-vocab:requestURI": "https://www.w3.org/WAI/content-assets/wcag-act-rules/testcases/ucwvc8/b1a2ce0c3435765e96d31a3262f1ed8c1d92f817.html"
        },
        {
          "@type": [
            "http-vocab:Message",
            "http-vocab:Response"
          ],
          "http-vocab:body": {
            "@type": [
              "cnt:Content",
              "cnt:ContentAsText"
            ],
            "cnt:characterEncoding": "utf-8",
            "cnt:chars": "<!DOCTYPE html>\n<html lang=\"da\">\n\t<head>\n\t\t<title>ACT Rules Format 1.0 - Abstract</title>\n\t</head>\n\t<body>\n\t\t<p>\n\t\t\tThe Accessibility Conformance Testing (ACT) Rules Format 1.0 defines a format for writing accessibility test\n\t\t\trules. These test rules can be used for developing automated testing tools and manual testing methodologies. It\n\t\t\tprovides a common format that allows any party involved in accessibility testing to document and share their\n\t\t\ttesting procedures in a robust and understandable manner. This enables transparency and harmonization of testing\n\t\t\tmethods, including methods implemented by accessibility test tools.\n\t\t</p>\n\t</body>\n</html>"
          },
          "http-vocab:headers": {
            "@list": [
              {
                "@type": "http-vocab:MessageHeader",
                "http-vocab:fieldName": "content-type",
                "http-vocab:fieldValue": "text/html; charset=utf-8"
              }
            ]
          },
          "http-vocab:statusCodeValue": 200
        }
      ],
      "url": "https://www.w3.org/WAI/content-assets/wcag-act-rules/testcases/ucwvc8/b1a2ce0c3435765e96d31a3262f1ed8c1d92f817.html"
    },
    {
      "@type": "Assertion",
      "earl:mode": "earl:semiAuto",
      "result": {
        "@type": "TestResult",
        "info": "The document's `lang` attribute (da) does not match its language (en)",
        "outcome": "earl:failed",
        "earl:pointer": {
          "@type": [
            "ptr:Pointer",
            "ptr:SinglePointer",
            "ptr:ExpressionPointer",
            "ptr:XPathPointer"
          ],
          "ptr:expression": "/"
        }
      },
      "subject": {
        "@id": "https://www.w3.org/WAI/content-assets/wcag-act-rules/testcases/ucwvc8/b1a2ce0c3435765e96d31a3262f1ed8c1d92f817.html"
      },
      "test": {
        "@id": "https://alfa.siteimprove.com/rules/sia-r109",
        "@type": [
          "TestCriterion",
          "TestCase"
        ],
        "isPartOf": [
          {
            "@id": "WCAG2:language-of-page",
            "@type": [
              "TestCriterion",
              "TestRequirement"
            ],
            "dct:isPartOf": "https://www.w3.org/TR/WCAG/",
            "title": "Language of Page"
          },
          {
            "@id": "https://www.w3.org/WAI/WCAG21/Techniques/html/H57",
            "@type": [
              "TestCriterion",
              "TestRequirement"
            ],
            "dct:isPartOf": "https://www.w3.org/WAI/WCAG21/Techniques/",
            "title": "Using the language attribute on the HTML element"
          }
        ]
      }
    },
    {
      "@id": "https://www.w3.org/WAI/content-assets/wcag-act-rules/testcases/ucwvc8/96785fb73282803fa4ca791ffdc0c3bc46b90702.html",
      "@type": "TestSubject",
      "dct:hasPart": [
        {
          "@type": [
            "http-vocab:Message",
            "http-vocab:Request"
          ],
          "http-vocab:body": {
            "@type": [
              "cnt:Content",
              "cnt:ContentAsText"
            ],
            "cnt:characterEncoding": "utf-8",
            "cnt:chars": ""
          },
          "http-vocab:headers": {
            "@list": []
          },
          "http-vocab:methodName": "GET",
          "http-vocab:requestURI": "https://www.w3.org/WAI/content-assets/wcag-act-rules/testcases/ucwvc8/96785fb73282803fa4ca791ffdc0c3bc46b90702.html"
        },
        {
          "@type": [
            "http-vocab:Message",
            "http-vocab:Response"
          ],
          "http-vocab:body": {
            "@type": [
              "cnt:Content",
              "cnt:ContentAsText"
            ],
            "cnt:characterEncoding": "utf-8",
            "cnt:chars": "<!DOCTYPE html>\n<html lang=\"en\">\n\t<head>\n\t\t<title>ACT Rules Format 1.0 - Abstract</title>\n\t</head>\n\t<body>\n\t\t<p>\n\t\t\tThe Accessibility Conformance Testing (ACT) Rules Format 1.0 defines a format for writing accessibility test\n\t\t\trules. These test rules can be used for developing automated testing tools and manual testing methodologies. It\n\t\t\tprovides a common format that allows any party involved in accessibility testing to document and share their\n\t\t\ttesting procedures in a robust and understandable manner. This enables transparency and harmonization of testing\n\t\t\tmethods, including methods implemented by accessibility test tools.\n\t\t</p>\n\t</body>\n</html>"
          },
          "http-vocab:headers": {
            "@list": [
              {
                "@type": "http-vocab:MessageHeader",
                "http-vocab:fieldName": "content-type",
                "http-vocab:fieldValue": "text/html; charset=utf-8"
              }
            ]
          },
          "http-vocab:statusCodeValue": 200
        }
      ],
      "url": "https://www.w3.org/WAI/content-assets/wcag-act-rules/testcases/ucwvc8/96785fb73282803fa4ca791ffdc0c3bc46b90702.html"
    },
    {
      "@type": "Assertion",
      "earl:mode": "earl:semiAuto",
      "result": {
        "@type": "TestResult",
        "info": "The document's `lang` attribute (en) matches its language (en)",
        "outcome": "earl:passed",
        "earl:pointer": {
          "@type": [
            "ptr:Pointer",
            "ptr:SinglePointer",
            "ptr:ExpressionPointer",
            "ptr:XPathPointer"
          ],
          "ptr:expression": "/"
        }
      },
      "subject": {
        "@id": "https://www.w3.org/WAI/content-assets/wcag-act-rules/testcases/ucwvc8/96785fb73282803fa4ca791ffdc0c3bc46b90702.html"
      },
      "test": {
        "@id": "https://alfa.siteimprove.com/rules/sia-r109",
        "@type": [
          "TestCriterion",
          "TestCase"
        ],
        "isPartOf": [
          {
            "@id": "WCAG2:language-of-page",
            "@type": [
              "TestCriterion",
              "TestRequirement"
            ],
            "dct:isPartOf": "https://www.w3.org/TR/WCAG/",
            "title": "Language of Page"
          },
          {
            "@id": "https://www.w3.org/WAI/WCAG21/Techniques/html/H57",
            "@type": [
              "TestCriterion",
              "TestRequirement"
            ],
            "dct:isPartOf": "https://www.w3.org/WAI/WCAG21/Techniques/",
            "title": "Using the language attribute on the HTML element"
          }
        ]
      }
    },
    {
      "@id": "https://www.w3.org/WAI/content-assets/wcag-act-rules/testcases/ucwvc8/941efb7368e46b27b937d34b07fc4d41da01b002.html",
      "@type": "TestSubject",
      "dct:hasPart": [
        {
          "@type": [
            "http-vocab:Message",
            "http-vocab:Request"
          ],
          "http-vocab:body": {
            "@type": [
              "cnt:Content",
              "cnt:ContentAsText"
            ],
            "cnt:characterEncoding": "utf-8",
            "cnt:chars": ""
          },
          "http-vocab:headers": {
            "@list": []
          },
          "http-vocab:methodName": "GET",
          "http-vocab:requestURI": "https://www.w3.org/WAI/content-assets/wcag-act-rules/testcases/ucwvc8/941efb7368e46b27b937d34b07fc4d41da01b002.html"
        },
        {
          "@type": [
            "http-vocab:Message",
            "http-vocab:Response"
          ],
          "http-vocab:body": {
            "@type": [
              "cnt:Content",
              "cnt:ContentAsText"
            ],
            "cnt:characterEncoding": "utf-8",
            "cnt:chars": "<!DOCTYPE html>\n<html></html>"
          },
          "http-vocab:headers": {
            "@list": [
              {
                "@type": "http-vocab:MessageHeader",
                "http-vocab:fieldName": "content-type",
                "http-vocab:fieldValue": "text/html; charset=utf-8"
              }
            ]
          },
          "http-vocab:statusCodeValue": 200
        }
      ],
      "url": "https://www.w3.org/WAI/content-assets/wcag-act-rules/testcases/ucwvc8/941efb7368e46b27b937d34b07fc4d41da01b002.html"
    },
    {
      "@type": "Assertion",
      "earl:mode": "earl:automatic",
      "result": {
        "@type": "TestResult",
        "outcome": "earl:inapplicable"
      },
      "subject": {
        "@id": "https://www.w3.org/WAI/content-assets/wcag-act-rules/testcases/ucwvc8/941efb7368e46b27b937d34b07fc4d41da01b002.html"
      },
      "test": {
        "@id": "https://alfa.siteimprove.com/rules/sia-r109",
        "@type": [
          "TestCriterion",
          "TestCase"
        ],
        "isPartOf": [
          {
            "@id": "WCAG2:language-of-page",
            "@type": [
              "TestCriterion",
              "TestRequirement"
            ],
            "dct:isPartOf": "https://www.w3.org/TR/WCAG/",
            "title": "Language of Page"
          },
          {
            "@id": "https://www.w3.org/WAI/WCAG21/Techniques/html/H57",
            "@type": [
              "TestCriterion",
              "TestRequirement"
            ],
            "dct:isPartOf": "https://www.w3.org/WAI/WCAG21/Techniques/",
            "title": "Using the language attribute on the HTML element"
          }
        ]
      }
    },
    {
      "@id": "https://www.w3.org/WAI/content-assets/wcag-act-rules/testcases/ucwvc8/864ccfb9bdb2c7f797602c5e4f25d1a0ad2aad7c.html",
      "@type": "TestSubject",
      "dct:hasPart": [
        {
          "@type": [
            "http-vocab:Message",
            "http-vocab:Request"
          ],
          "http-vocab:body": {
            "@type": [
              "cnt:Content",
              "cnt:ContentAsText"
            ],
            "cnt:characterEncoding": "utf-8",
            "cnt:chars": ""
          },
          "http-vocab:headers": {
            "@list": []
          },
          "http-vocab:methodName": "GET",
          "http-vocab:requestURI": "https://www.w3.org/WAI/content-assets/wcag-act-rules/testcases/ucwvc8/864ccfb9bdb2c7f797602c5e4f25d1a0ad2aad7c.html"
        },
        {
          "@type": [
            "http-vocab:Message",
            "http-vocab:Response"
          ],
          "http-vocab:body": {
            "@type": [
              "cnt:Content",
              "cnt:ContentAsText"
            ],
            "cnt:characterEncoding": "utf-8",
            "cnt:chars": "<!DOCTYPE html>\n<html lang=\"nl\">\n\t<head>\n\t\t<title>Paris</title>\n\t</head>\n\t<body>\n\t\t<img src=\"/WAI/content-assets/wcag-act-rules/test-assets/shared/fireworks.jpg\" aria-labelledby=\"caption\" />\n\t\t<p lang=\"en\" id=\"caption\" hidden>\n\t\t\tFireworks over Paris!\n\t\t</p>\n\t</body>\n</html>"
          },
          "http-vocab:headers": {
            "@list": [
              {
                "@type": "http-vocab:MessageHeader",
                "http-vocab:fieldName": "content-type",
                "http-vocab:fieldValue": "text/html; charset=utf-8"
              }
            ]
          },
          "http-vocab:statusCodeValue": 200
        }
      ],
      "url": "https://www.w3.org/WAI/content-assets/wcag-act-rules/testcases/ucwvc8/864ccfb9bdb2c7f797602c5e4f25d1a0ad2aad7c.html"
    },
    {
      "@type": "Assertion",
      "earl:mode": "earl:semiAuto",
      "result": {
        "@type": "TestResult",
        "info": "The document's `lang` attribute (nl) does not match its language (en)",
        "outcome": "earl:failed",
        "earl:pointer": {
          "@type": [
            "ptr:Pointer",
            "ptr:SinglePointer",
            "ptr:ExpressionPointer",
            "ptr:XPathPointer"
          ],
          "ptr:expression": "/"
        }
      },
      "subject": {
        "@id": "https://www.w3.org/WAI/content-assets/wcag-act-rules/testcases/ucwvc8/864ccfb9bdb2c7f797602c5e4f25d1a0ad2aad7c.html"
      },
      "test": {
        "@id": "https://alfa.siteimprove.com/rules/sia-r109",
        "@type": [
          "TestCriterion",
          "TestCase"
        ],
        "isPartOf": [
          {
            "@id": "WCAG2:language-of-page",
            "@type": [
              "TestCriterion",
              "TestRequirement"
            ],
            "dct:isPartOf": "https://www.w3.org/TR/WCAG/",
            "title": "Language of Page"
          },
          {
            "@id": "https://www.w3.org/WAI/WCAG21/Techniques/html/H57",
            "@type": [
              "TestCriterion",
              "TestRequirement"
            ],
            "dct:isPartOf": "https://www.w3.org/WAI/WCAG21/Techniques/",
            "title": "Using the language attribute on the HTML element"
          }
        ]
      }
    },
    {
      "@id": "https://www.w3.org/WAI/content-assets/wcag-act-rules/testcases/ucwvc8/c4eaf50df4fa37f931374c74ac369a018b780ec6.html",
      "@type": "TestSubject",
      "dct:hasPart": [
        {
          "@type": [
            "http-vocab:Message",
            "http-vocab:Request"
          ],
          "http-vocab:body": {
            "@type": [
              "cnt:Content",
              "cnt:ContentAsText"
            ],
            "cnt:characterEncoding": "utf-8",
            "cnt:chars": ""
          },
          "http-vocab:headers": {
            "@list": []
          },
          "http-vocab:methodName": "GET",
          "http-vocab:requestURI": "https://www.w3.org/WAI/content-assets/wcag-act-rules/testcases/ucwvc8/c4eaf50df4fa37f931374c74ac369a018b780ec6.html"
        },
        {
          "@type": [
            "http-vocab:Message",
            "http-vocab:Response"
          ],
          "http-vocab:body": {
            "@type": [
              "cnt:Content",
              "cnt:ContentAsText"
            ],
            "cnt:characterEncoding": "utf-8",
            "cnt:chars": "<!DOCTYPE html>\n<html lang=\"nl\">\n\t<head>\n\t\t<title>Fireworks over Paris</title>\n\t</head>\n\t<body>\n\t\t<img src=\"/WAI/content-assets/wcag-act-rules/test-assets/shared/fireworks.jpg\" alt=\"Fireworks over Paris\" />\n\t\t<p lang=\"nl\">\n\t\t\tGelukkig nieuwjaar!\n\t\t</p>\n\t</body>\n</html>"
          },
          "http-vocab:headers": {
            "@list": [
              {
                "@type": "http-vocab:MessageHeader",
                "http-vocab:fieldName": "content-type",
                "http-vocab:fieldValue": "text/html; charset=utf-8"
              }
            ]
          },
          "http-vocab:statusCodeValue": 200
        }
      ],
      "url": "https://www.w3.org/WAI/content-assets/wcag-act-rules/testcases/ucwvc8/c4eaf50df4fa37f931374c74ac369a018b780ec6.html"
    },
    {
      "@type": "Assertion",
      "earl:mode": "earl:semiAuto",
      "result": {
        "@type": "TestResult",
        "info": "The document's `lang` attribute (nl) does not match its language (en)",
        "outcome": "earl:failed",
        "earl:pointer": {
          "@type": [
            "ptr:Pointer",
            "ptr:SinglePointer",
            "ptr:ExpressionPointer",
            "ptr:XPathPointer"
          ],
          "ptr:expression": "/"
        }
      },
      "subject": {
        "@id": "https://www.w3.org/WAI/content-assets/wcag-act-rules/testcases/ucwvc8/c4eaf50df4fa37f931374c74ac369a018b780ec6.html"
      },
      "test": {
        "@id": "https://alfa.siteimprove.com/rules/sia-r109",
        "@type": [
          "TestCriterion",
          "TestCase"
        ],
        "isPartOf": [
          {
            "@id": "WCAG2:language-of-page",
            "@type": [
              "TestCriterion",
              "TestRequirement"
            ],
            "dct:isPartOf": "https://www.w3.org/TR/WCAG/",
            "title": "Language of Page"
          },
          {
            "@id": "https://www.w3.org/WAI/WCAG21/Techniques/html/H57",
            "@type": [
              "TestCriterion",
              "TestRequirement"
            ],
            "dct:isPartOf": "https://www.w3.org/WAI/WCAG21/Techniques/",
            "title": "Using the language attribute on the HTML element"
          }
        ]
      }
    },
    {
      "@id": "https://www.w3.org/WAI/content-assets/wcag-act-rules/testcases/ucwvc8/61b97f487132c7aca3dd9787e9ff1454903d45fb.html",
      "@type": "TestSubject",
      "dct:hasPart": [
        {
          "@type": [
            "http-vocab:Message",
            "http-vocab:Request"
          ],
          "http-vocab:body": {
            "@type": [
              "cnt:Content",
              "cnt:ContentAsText"
            ],
            "cnt:characterEncoding": "utf-8",
            "cnt:chars": ""
          },
          "http-vocab:headers": {
            "@list": []
          },
          "http-vocab:methodName": "GET",
          "http-vocab:requestURI": "https://www.w3.org/WAI/content-assets/wcag-act-rules/testcases/ucwvc8/61b97f487132c7aca3dd9787e9ff1454903d45fb.html"
        },
        {
          "@type": [
            "http-vocab:Message",
            "http-vocab:Response"
          ],
          "http-vocab:body": {
            "@type": [
              "cnt:Content",
              "cnt:ContentAsText"
            ],
            "cnt:characterEncoding": "utf-8",
            "cnt:chars": "<!DOCTYPE html>\n<html lang=\"en\">\n\t<head>\n\t\t<title>Met de kippen op stok</title>\n\t</head>\n\t<body>\n\t\t<blockquote>\n\t\t\t<p>\"Hij ging met de kippen op stok\"</p>\n\t\t</blockquote>\n\t\t<p lang=\"en\">\n\t\t\tThis Dutch phrase literally translates into \"He went to roost with the chickens\", but it means that he went to bed\n\t\t\tearly.\n\t\t</p>\n\t</body>\n</html>"
          },
          "http-vocab:headers": {
            "@list": [
              {
                "@type": "http-vocab:MessageHeader",
                "http-vocab:fieldName": "content-type",
                "http-vocab:fieldValue": "text/html; charset=utf-8"
              }
            ]
          },
          "http-vocab:statusCodeValue": 200
        }
      ],
      "url": "https://www.w3.org/WAI/content-assets/wcag-act-rules/testcases/ucwvc8/61b97f487132c7aca3dd9787e9ff1454903d45fb.html"
    },
    {
      "@type": "Assertion",
      "earl:mode": "earl:semiAuto",
      "result": {
        "@type": "TestResult",
        "info": "The document's `lang` attribute (en) does not match its language (nl)",
        "outcome": "earl:failed",
        "earl:pointer": {
          "@type": [
            "ptr:Pointer",
            "ptr:SinglePointer",
            "ptr:ExpressionPointer",
            "ptr:XPathPointer"
          ],
          "ptr:expression": "/"
        }
      },
      "subject": {
        "@id": "https://www.w3.org/WAI/content-assets/wcag-act-rules/testcases/ucwvc8/61b97f487132c7aca3dd9787e9ff1454903d45fb.html"
      },
      "test": {
        "@id": "https://alfa.siteimprove.com/rules/sia-r109",
        "@type": [
          "TestCriterion",
          "TestCase"
        ],
        "isPartOf": [
          {
            "@id": "WCAG2:language-of-page",
            "@type": [
              "TestCriterion",
              "TestRequirement"
            ],
            "dct:isPartOf": "https://www.w3.org/TR/WCAG/",
            "title": "Language of Page"
          },
          {
            "@id": "https://www.w3.org/WAI/WCAG21/Techniques/html/H57",
            "@type": [
              "TestCriterion",
              "TestRequirement"
            ],
            "dct:isPartOf": "https://www.w3.org/WAI/WCAG21/Techniques/",
            "title": "Using the language attribute on the HTML element"
          }
        ]
      }
    },
    {
      "@id": "https://www.w3.org/WAI/content-assets/wcag-act-rules/testcases/ucwvc8/cd7898c9fcd7d06565cd55393310c2600ffc070f.html",
      "@type": "TestSubject",
      "dct:hasPart": [
        {
          "@type": [
            "http-vocab:Message",
            "http-vocab:Request"
          ],
          "http-vocab:body": {
            "@type": [
              "cnt:Content",
              "cnt:ContentAsText"
            ],
            "cnt:characterEncoding": "utf-8",
            "cnt:chars": ""
          },
          "http-vocab:headers": {
            "@list": []
          },
          "http-vocab:methodName": "GET",
          "http-vocab:requestURI": "https://www.w3.org/WAI/content-assets/wcag-act-rules/testcases/ucwvc8/cd7898c9fcd7d06565cd55393310c2600ffc070f.html"
        },
        {
          "@type": [
            "http-vocab:Message",
            "http-vocab:Response"
          ],
          "http-vocab:body": {
            "@type": [
              "cnt:Content",
              "cnt:ContentAsText"
            ],
            "cnt:characterEncoding": "utf-8",
            "cnt:chars": "<!DOCTYPE html>\n<html lang=\"EN\">\n\t<head>\n\t\t<title>Gelukkig</title>\n\t</head>\n\t<body>\n\t\t<p>The Dutch word \"gelukkig\" has no equivalent in English.</p>\n\t</body>\n</html>"
          },
          "http-vocab:headers": {
            "@list": [
              {
                "@type": "http-vocab:MessageHeader",
                "http-vocab:fieldName": "content-type",
                "http-vocab:fieldValue": "text/html; charset=utf-8"
              }
            ]
          },
          "http-vocab:statusCodeValue": 200
        }
      ],
      "url": "https://www.w3.org/WAI/content-assets/wcag-act-rules/testcases/ucwvc8/cd7898c9fcd7d06565cd55393310c2600ffc070f.html"
    },
    {
      "@type": "Assertion",
      "earl:mode": "earl:semiAuto",
      "result": {
        "@type": "TestResult",
        "info": "The document's `lang` attribute (en) matches its language (en)",
        "outcome": "earl:passed",
        "earl:pointer": {
          "@type": [
            "ptr:Pointer",
            "ptr:SinglePointer",
            "ptr:ExpressionPointer",
            "ptr:XPathPointer"
          ],
          "ptr:expression": "/"
        }
      },
      "subject": {
        "@id": "https://www.w3.org/WAI/content-assets/wcag-act-rules/testcases/ucwvc8/cd7898c9fcd7d06565cd55393310c2600ffc070f.html"
      },
      "test": {
        "@id": "https://alfa.siteimprove.com/rules/sia-r109",
        "@type": [
          "TestCriterion",
          "TestCase"
        ],
        "isPartOf": [
          {
            "@id": "WCAG2:language-of-page",
            "@type": [
              "TestCriterion",
              "TestRequirement"
            ],
            "dct:isPartOf": "https://www.w3.org/TR/WCAG/",
            "title": "Language of Page"
          },
          {
            "@id": "https://www.w3.org/WAI/WCAG21/Techniques/html/H57",
            "@type": [
              "TestCriterion",
              "TestRequirement"
            ],
            "dct:isPartOf": "https://www.w3.org/WAI/WCAG21/Techniques/",
            "title": "Using the language attribute on the HTML element"
          }
        ]
      }
    },
    {
      "@id": "https://www.w3.org/WAI/content-assets/wcag-act-rules/testcases/ucwvc8/5f654ecf0b7a0af4d0ba120a5cd1db2761ffa79c.html",
      "@type": "TestSubject",
      "dct:hasPart": [
        {
          "@type": [
            "http-vocab:Message",
            "http-vocab:Request"
          ],
          "http-vocab:body": {
            "@type": [
              "cnt:Content",
              "cnt:ContentAsText"
            ],
            "cnt:characterEncoding": "utf-8",
            "cnt:chars": ""
          },
          "http-vocab:headers": {
            "@list": []
          },
          "http-vocab:methodName": "GET",
          "http-vocab:requestURI": "https://www.w3.org/WAI/content-assets/wcag-act-rules/testcases/ucwvc8/5f654ecf0b7a0af4d0ba120a5cd1db2761ffa79c.html"
        },
        {
          "@type": [
            "http-vocab:Message",
            "http-vocab:Response"
          ],
          "http-vocab:body": {
            "@type": [
              "cnt:Content",
              "cnt:ContentAsText"
            ],
            "cnt:characterEncoding": "utf-8",
            "cnt:chars": "<!DOCTYPE html>\n<html lang=\"nl\">\n\t<head>\n\t\t<title>Met de kippen op stok</title>\n\t</head>\n\t<body>\n\t\t<blockquote>\n\t\t\t<p>\"Hij ging met de kippen op stok\"</p>\n\t\t</blockquote>\n\t\t<p lang=\"en\">\n\t\t\tThis Dutch phrase literally translates into \"He went to roost with the chickens\", but it means that he went to bed\n\t\t\tearly.\n\t\t</p>\n\t</body>\n</html>"
          },
          "http-vocab:headers": {
            "@list": [
              {
                "@type": "http-vocab:MessageHeader",
                "http-vocab:fieldName": "content-type",
                "http-vocab:fieldValue": "text/html; charset=utf-8"
              }
            ]
          },
          "http-vocab:statusCodeValue": 200
        }
      ],
      "url": "https://www.w3.org/WAI/content-assets/wcag-act-rules/testcases/ucwvc8/5f654ecf0b7a0af4d0ba120a5cd1db2761ffa79c.html"
    },
    {
      "@type": "Assertion",
      "earl:mode": "earl:semiAuto",
      "result": {
        "@type": "TestResult",
        "info": "The document's `lang` attribute (nl) matches its language (nl)",
        "outcome": "earl:passed",
        "earl:pointer": {
          "@type": [
            "ptr:Pointer",
            "ptr:SinglePointer",
            "ptr:ExpressionPointer",
            "ptr:XPathPointer"
          ],
          "ptr:expression": "/"
        }
      },
      "subject": {
        "@id": "https://www.w3.org/WAI/content-assets/wcag-act-rules/testcases/ucwvc8/5f654ecf0b7a0af4d0ba120a5cd1db2761ffa79c.html"
      },
      "test": {
        "@id": "https://alfa.siteimprove.com/rules/sia-r109",
        "@type": [
          "TestCriterion",
          "TestCase"
        ],
        "isPartOf": [
          {
            "@id": "WCAG2:language-of-page",
            "@type": [
              "TestCriterion",
              "TestRequirement"
            ],
            "dct:isPartOf": "https://www.w3.org/TR/WCAG/",
            "title": "Language of Page"
          },
          {
            "@id": "https://www.w3.org/WAI/WCAG21/Techniques/html/H57",
            "@type": [
              "TestCriterion",
              "TestRequirement"
            ],
            "dct:isPartOf": "https://www.w3.org/WAI/WCAG21/Techniques/",
            "title": "Using the language attribute on the HTML element"
          }
        ]
      }
    },
    {
      "@id": "https://www.w3.org/WAI/content-assets/wcag-act-rules/testcases/ucwvc8/b64d767d873269ff00966630e34ab198fc24368f.html",
      "@type": "TestSubject",
      "dct:hasPart": [
        {
          "@type": [
            "http-vocab:Message",
            "http-vocab:Request"
          ],
          "http-vocab:body": {
            "@type": [
              "cnt:Content",
              "cnt:ContentAsText"
            ],
            "cnt:characterEncoding": "utf-8",
            "cnt:chars": ""
          },
          "http-vocab:headers": {
            "@list": []
          },
          "http-vocab:methodName": "GET",
          "http-vocab:requestURI": "https://www.w3.org/WAI/content-assets/wcag-act-rules/testcases/ucwvc8/b64d767d873269ff00966630e34ab198fc24368f.html"
        },
        {
          "@type": [
            "http-vocab:Message",
            "http-vocab:Response"
          ],
          "http-vocab:body": {
            "@type": [
              "cnt:Content",
              "cnt:ContentAsText"
            ],
            "cnt:characterEncoding": "utf-8",
            "cnt:chars": "<!DOCTYPE html>\n<html lang=\"i-lux\">\n\t<body>\n\t\t<p lang=\"lb\">Lëtzebuerg ass e Land an Europa.</p>\n\t</body>\n</html>"
          },
          "http-vocab:headers": {
            "@list": [
              {
                "@type": "http-vocab:MessageHeader",
                "http-vocab:fieldName": "content-type",
                "http-vocab:fieldValue": "text/html; charset=utf-8"
              }
            ]
          },
          "http-vocab:statusCodeValue": 200
        }
      ],
      "url": "https://www.w3.org/WAI/content-assets/wcag-act-rules/testcases/ucwvc8/b64d767d873269ff00966630e34ab198fc24368f.html"
    },
    {
      "@type": "Assertion",
      "earl:mode": "earl:automatic",
      "result": {
        "@type": "TestResult",
        "outcome": "earl:inapplicable"
      },
      "subject": {
        "@id": "https://www.w3.org/WAI/content-assets/wcag-act-rules/testcases/ucwvc8/b64d767d873269ff00966630e34ab198fc24368f.html"
      },
      "test": {
        "@id": "https://alfa.siteimprove.com/rules/sia-r109",
        "@type": [
          "TestCriterion",
          "TestCase"
        ],
        "isPartOf": [
          {
            "@id": "WCAG2:language-of-page",
            "@type": [
              "TestCriterion",
              "TestRequirement"
            ],
            "dct:isPartOf": "https://www.w3.org/TR/WCAG/",
            "title": "Language of Page"
          },
          {
            "@id": "https://www.w3.org/WAI/WCAG21/Techniques/html/H57",
            "@type": [
              "TestCriterion",
              "TestRequirement"
            ],
            "dct:isPartOf": "https://www.w3.org/WAI/WCAG21/Techniques/",
            "title": "Using the language attribute on the HTML element"
          }
        ]
      }
    },
    {
      "@id": "https://www.w3.org/WAI/content-assets/wcag-act-rules/testcases/ucwvc8/a67210a4d3e4db840309518c1ec557459b709206.html",
      "@type": "TestSubject",
      "dct:hasPart": [
        {
          "@type": [
            "http-vocab:Message",
            "http-vocab:Request"
          ],
          "http-vocab:body": {
            "@type": [
              "cnt:Content",
              "cnt:ContentAsText"
            ],
            "cnt:characterEncoding": "utf-8",
            "cnt:chars": ""
          },
          "http-vocab:headers": {
            "@list": []
          },
          "http-vocab:methodName": "GET",
          "http-vocab:requestURI": "https://www.w3.org/WAI/content-assets/wcag-act-rules/testcases/ucwvc8/a67210a4d3e4db840309518c1ec557459b709206.html"
        },
        {
          "@type": [
            "http-vocab:Message",
            "http-vocab:Response"
          ],
          "http-vocab:body": {
            "@type": [
              "cnt:Content",
              "cnt:ContentAsText"
            ],
            "cnt:characterEncoding": "utf-8",
            "cnt:chars": "<!DOCTYPE html>\n<html lang=\"en\">\n\t<head>\n\t\t<title>Fireworks over Paris</title>\n\t</head>\n\t<body>\n\t\t<img src=\"/WAI/content-assets/wcag-act-rules/test-assets/shared/fireworks.jpg\" alt=\"Fireworks over Paris\" />\n\t\t<p lang=\"nl\">\n\t\t\tGelukkig nieuwjaar!\n\t\t</p>\n\t</body>\n</html>"
          },
          "http-vocab:headers": {
            "@list": [
              {
                "@type": "http-vocab:MessageHeader",
                "http-vocab:fieldName": "content-type",
                "http-vocab:fieldValue": "text/html; charset=utf-8"
              }
            ]
          },
          "http-vocab:statusCodeValue": 200
        }
      ],
      "url": "https://www.w3.org/WAI/content-assets/wcag-act-rules/testcases/ucwvc8/a67210a4d3e4db840309518c1ec557459b709206.html"
    },
    {
      "@type": "Assertion",
      "earl:mode": "earl:semiAuto",
      "result": {
        "@type": "TestResult",
        "info": "The document's `lang` attribute (en) matches its language (en)",
        "outcome": "earl:passed",
        "earl:pointer": {
          "@type": [
            "ptr:Pointer",
            "ptr:SinglePointer",
            "ptr:ExpressionPointer",
            "ptr:XPathPointer"
          ],
          "ptr:expression": "/"
        }
      },
      "subject": {
        "@id": "https://www.w3.org/WAI/content-assets/wcag-act-rules/testcases/ucwvc8/a67210a4d3e4db840309518c1ec557459b709206.html"
      },
      "test": {
        "@id": "https://alfa.siteimprove.com/rules/sia-r109",
        "@type": [
          "TestCriterion",
          "TestCase"
        ],
        "isPartOf": [
          {
            "@id": "WCAG2:language-of-page",
            "@type": [
              "TestCriterion",
              "TestRequirement"
            ],
            "dct:isPartOf": "https://www.w3.org/TR/WCAG/",
            "title": "Language of Page"
          },
          {
            "@id": "https://www.w3.org/WAI/WCAG21/Techniques/html/H57",
            "@type": [
              "TestCriterion",
              "TestRequirement"
            ],
            "dct:isPartOf": "https://www.w3.org/WAI/WCAG21/Techniques/",
            "title": "Using the language attribute on the HTML element"
          }
        ]
      }
    }
  ]
}